{
    "version": "2.7.0",
    "architecture": {
        "32bit": {
            "url": "https://github.com/twpayne/chezmoi/releases/download/v2.7.0/chezmoi_2.7.0_windows_i386.zip",
            "bin": [
                "chezmoi.exe"
            ],
            "hash": "288587c02064777651cbf5877dfbcafebe1c23d79a7dd93cd27d152c5a6c8ffb"
        },
        "64bit": {
            "url": "https://github.com/twpayne/chezmoi/releases/download/v2.7.0/chezmoi_2.7.0_windows_amd64.zip",
            "bin": [
                "chezmoi.exe"
            ],
            "hash": "542df70ffe83b374010670834f2cf91cd5763731720835e260f73b40bb99cf4d"
        }
    },
    "homepage": "https://chezmoi.io",
    "license": "MIT",
    "description": "Manage your dotfiles across multiple diverse machines, securely."
}